run_lambda/__gen_context.py
run_lambda/__init__.py
run_lambda/__main__.py
run_lambda/call.py
run_lambda/context.py
run_lambda/utils.py
run_lambda-0.1.7.2.dist-info/DESCRIPTION.rst
run_lambda-0.1.7.2.dist-info/METADATA
run_lambda-0.1.7.2.dist-info/RECORD
run_lambda-0.1.7.2.dist-info/WHEEL
run_lambda-0.1.7.2.dist-info/entry_points.txt
run_lambda-0.1.7.2.dist-info/metadata.json
run_lambda-0.1.7.2.dist-info/top_level.txt
tests/__init__.py
tests/square_root.py
tests/test.py
tests/test_cli.py
