Metadata-Version: 2.0
Name: run-lambda
Version: 0.1.7.2
Summary: Run AWS Lambda functions locally
Home-page: https://github.com/ethantkoenig/run_lambda
Author: Ethan Koenig
Author-email: ethantkoenig@gmail.com
License: MIT
Keywords: aws,lambda,run,local,locally
Platform: UNKNOWN
Classifier: License :: OSI Approved :: MIT License
Classifier: Programming Language :: Python :: 2.7
Classifier: Programming Language :: Python :: 3
Classifier: Programming Language :: Python :: 3.3
Classifier: Programming Language :: Python :: 3.4
Classifier: Programming Language :: Python :: 3.5
Requires-Dist: memory-profiler
Requires-Dist: mock
Requires-Dist: psutil
Requires-Dist: six
